{"cameraMode":{"drawMode":0,"name":"Shaded","section":"Shading Mode"},"sceneLighting":true,"audioPlay":false,"sceneViewState":{"m_AlwaysRefresh":false,"showFog":true,"showSkybox":true,"showFlares":true,"showImageEffects":true,"showParticleSystems":true,"showVisualEffectGraphs":true,"m_FxEnabled":true},"in2DMode":false,"pivot":{"x":510.9581604003906,"y":289.4432373046875,"z":-29.253173828125},"rotation":{"x":0.08838547766208649,"y":-0.001494100783020258,"z":0.00013414889690466225,"w":0.9960954785346985},"size":566.7508544921875,"orthographic":false}